paper_asset_pricing/__init__.py
paper_asset_pricing/__main__.py
paper_asset_pricing/cli.py
paper_asset_pricing/templates/data-config.yaml.template
paper_asset_pricing/templates/gitignore.template
paper_asset_pricing/templates/models-config.yaml.template
paper_asset_pricing/templates/paper-project.yaml.template
paper_asset_pricing/templates/portfolio-config.yaml.template
paper_asset_pricing/templates/project_readme.md.template
paper_asset_pricing-0.1.3.dist-info/METADATA
paper_asset_pricing-0.1.3.dist-info/WHEEL
paper_asset_pricing-0.1.3.dist-info/entry_points.txt
paper_asset_pricing-0.1.3.dist-info/licenses/LICENSE
paper_asset_pricing-0.1.3.dist-info/RECORD
