Metadata-Version: 2.4
Name: paper-asset-pricing
Version: 0.1.3
Summary: A comprehensive suite of tools for research in asset pricing.
Author-email: Lorenzo Varese <55581163+lorenzovarese@users.noreply.github.com>
License-File: LICENSE
Requires-Python: >=3.11
Requires-Dist: jinja2>=3.1.6
Requires-Dist: pyyaml>=6.0.2
Requires-Dist: requests>=2.32.3
Requires-Dist: typer>=0.16.0
Provides-Extra: all
Requires-Dist: paper-data==0.1.2; extra == 'all'
Requires-Dist: paper-model==0.1.1; extra == 'all'
Requires-Dist: paper-portfolio==0.1.1; extra == 'all'
Provides-Extra: data
Requires-Dist: paper-data==0.1.2; extra == 'data'
Provides-Extra: model
Requires-Dist: paper-model==0.1.1; extra == 'model'
Provides-Extra: portfolio
Requires-Dist: paper-portfolio==0.1.1; extra == 'portfolio'
